CHANGES.txt
LICENSE.txt
MANIFEST.in
README.txt
setup.py
js/__init__.py
js.videojs.egg-info/PKG-INFO
js.videojs.egg-info/SOURCES.txt
js.videojs.egg-info/dependency_links.txt
js.videojs.egg-info/entry_points.txt
js.videojs.egg-info/namespace_packages.txt
js.videojs.egg-info/not-zip-safe
js.videojs.egg-info/requires.txt
js.videojs.egg-info/top_level.txt
js/videojs/__init__.py
js/videojs/test_video.js.txt
js/videojs/resources/video-js.css
js/videojs/resources/video-js.min.css
js/videojs/resources/video.cjs.js
js/videojs/resources/video.es.js
js/videojs/resources/video.js
js/videojs/resources/video.min.js
js/videojs/resources/alt/video-js-cdn.css
js/videojs/resources/alt/video-js-cdn.min.css
js/videojs/resources/alt/video.core.js
js/videojs/resources/alt/video.core.min.js
js/videojs/resources/alt/video.core.novtt.js
js/videojs/resources/alt/video.core.novtt.min.js
js/videojs/resources/alt/video.novtt.js
js/videojs/resources/alt/video.novtt.min.js
js/videojs/resources/font/VideoJS.svg
js/videojs/resources/font/VideoJS.ttf
js/videojs/resources/font/VideoJS.woff
js/videojs/resources/lang/ar.js
js/videojs/resources/lang/ar.json
js/videojs/resources/lang/ba.js
js/videojs/resources/lang/ba.json
js/videojs/resources/lang/bg.js
js/videojs/resources/lang/bg.json
js/videojs/resources/lang/ca.js
js/videojs/resources/lang/ca.json
js/videojs/resources/lang/cs.js
js/videojs/resources/lang/cs.json
js/videojs/resources/lang/cy.js
js/videojs/resources/lang/cy.json
js/videojs/resources/lang/da.js
js/videojs/resources/lang/da.json
js/videojs/resources/lang/de.js
js/videojs/resources/lang/de.json
js/videojs/resources/lang/el.js
js/videojs/resources/lang/el.json
js/videojs/resources/lang/en.js
js/videojs/resources/lang/en.json
js/videojs/resources/lang/es.js
js/videojs/resources/lang/es.json
js/videojs/resources/lang/fa.js
js/videojs/resources/lang/fa.json
js/videojs/resources/lang/fi.js
js/videojs/resources/lang/fi.json
js/videojs/resources/lang/fr.js
js/videojs/resources/lang/fr.json
js/videojs/resources/lang/gl.js
js/videojs/resources/lang/gl.json
js/videojs/resources/lang/he.js
js/videojs/resources/lang/he.json
js/videojs/resources/lang/hr.js
js/videojs/resources/lang/hr.json
js/videojs/resources/lang/hu.js
js/videojs/resources/lang/hu.json
