Metadata-Version: 1.0
Name: js.videojs
Version: 7.5.5
Summary: Fanstatic packaging of Video.js
Home-page: UNKNOWN
Author: Fanstatic Developers
Author-email: fanstatic@googlegroups.com
License: BSD
Platform: UNKNOWN
